literumilo/__init__.py
literumilo/example.py
literumilo/example.txt
literumilo/literumilo.py
literumilo/literumilo_check_word.py
literumilo/literumilo_ending.py
literumilo/literumilo_entry.py
literumilo/literumilo_load.py
literumilo/literumilo_morpheme_list.py
literumilo/literumilo_scan_morphemes.py
literumilo/literumilo_suffix.py
literumilo/literumilo_utils.py
literumilo/data/__init__.py
literumilo/data/vortaro.tsv
literumilo/tests/__init__.py
literumilo/tests/test.txt
literumilo/tests/test_literumilo.py
literumilo-1.0.8.dist-info/LICENSE
literumilo-1.0.8.dist-info/METADATA
literumilo-1.0.8.dist-info/WHEEL
literumilo-1.0.8.dist-info/top_level.txt
literumilo-1.0.8.dist-info/RECORD
