Metadata-Version: 2.1
Name: literumilo
Version: 1.0.8
Summary: A spell checker and morphological analyzer for Esperanto.
Home-page: https://github.com/Indrikoterio/literumilo
Author: Cleve (Klivo) Lendon
Author-email: indriko@yahoo.com
License: UNKNOWN
Platform: UNKNOWN
Classifier: Programming Language :: Python :: 3
Classifier: License :: Public Domain
Classifier: Operating System :: OS Independent
Requires-Python: >=3.5
